Workbook

Sheet Leia-me
A1: Ponte Solidária — Planilha de custos e viabilidade
A3: COMO USAR: altere apenas as células com texto AZUL (premissas). Células pretas são fórmulas e recalculam sozinhas.
A4: Células com fundo AMARELO são as premissas mais sensíveis (valor da hora de manutenção e investimento em marketing).
A5: Valores em reais (R$). Cenários: Piloto (TCC/Janaúba), Crescimento (região) e Consolidado (vários municípios).
A6: Fontes verificadas: domínio .com.br R$ 40,00/ano (registro.br); cotas gratuitas do Firestore no plano Spark: 50.000 leituras e 20.000 escritas por dia (documentação do Firebase);
A7: população de Janaúba 70.699 hab. (IBGE, Censo 2022); insegurança alimentar em 24,2% dos domicílios em 2024 (IBGE/PNAD Contínua).
A8: Os demais preços são ESTIMATIVAS DE MERCADO usadas como premissa: confirme com o fornecedor antes de contratar.
A9: Abas: Premissas · Custos · Capacidade Firebase · Público estimado · Financiamento

Sheet Premissas
A1: Premissa | B1: Piloto | C1: Crescimento | D1: Consolidado | E1: Observação
A2: Contas de pessoas (doadores/beneficiários) | B2: 250 | C2: 1000 | D2: 5000 | E2: Estimativa própria; ver aba Público estimado
A3: ONGs parceiras | B3: 3 | C3: 10 | D3: 30 | E3: Estimativa própria
A4: Usuários ativos por dia (% das contas) | B4: 0.1 | C4: 0.08 | D4: 0.06 | E4: Premissa: parte das contas acessa em um dia comum
A5: Leituras Firestore por visita | B5: 300 | C5: 300 | D5: 300 | E5: O site escuta coleções em tempo real; ajustável após medir no console
A6: Escritas Firestore por visita | B6: 8 | C6: 8 | D6: 8 | E6: Doações, pedidos, notificações, mensagens
A7: Visitas por usuário ativo por dia | B7: 1.5 | C7: 1.5 | D7: 1.5 | E7: Premissa
A8: Valor da hora de manutenção (R$/h) | B8: 60 | C8: 60 | D8: 60 | E8: Premissa de mercado (desenvolvedor júnior); no TCC pode ser voluntário
A9: Horas de manutenção por mês | B9: 4 | C9: 12 | D9: 30 | E9: Correções, atualização de bibliotecas, moderação técnica
A10: Horas de moderação/suporte por mês | B10: 4 | C10: 15 | D10: 40 | E10: Aprovar ONGs, bloquear abuso, atender dúvidas
A11: Investimento mensal em anúncios (R$) | B11: 0 | C11: 150 | D11: 500 | E11: Impulsionamento em redes sociais
A12: Cota gratuita: leituras/dia | B12: 50000 | C12: 50000 | D12: 50000 | E12: Firebase, plano Spark
A13: Cota gratuita: escritas/dia | B13: 20000 | C13: 20000 | D13: 20000 | E13: Firebase, plano Spark

Sheet Custos
A1: Categoria | B1: Item | C1: Piloto (R$/mês) | D1: Cresc. (R$/mês) | E1: Consol. (R$/mês) | F1: Piloto (R$/ano) | G1: Cresc. (R$/ano) | H1: Consol. (R$/ano) | I1: Observação
A2: Domínio | B2: Domínio .com.br (R$ 40,00/ano) | C2: =40/12 -> 3.3333333 | D2: =40/12 -> 3.3333333 | E2: =40/12 -> 3.3333333 | F2: =C2*12 -> 40 | G2: =D2*12 -> 40 | H2: =E2*12 -> 40 | I2: Fonte: registro.br — valor anual dividido por 12
A3: Hospedagem | B3: GitHub Pages / Firebase Hosting (site estático) | C3: 0 | D3: 0 | E3: 0 | F3: =C3*12 -> 0 | G3: =D3*12 -> 0 | H3: =E3*12 -> 0 | I3: Gratuito nos limites de uso
A4: Hospedagem | B4: Firebase Blaze (uso acima da cota gratuita) | C4: 0 | D4: 40 | E4: 150 | F4: =C4*12 -> 0 | G4: =D4*12 -> 480 | H4: =E4*12 -> 1800 | I4: Estimativa: só passa a cobrar quando excede as cotas; ver aba Capacidade
A5: Integrações | B5: Firebase Authentication e Firestore (Spark) | C5: 0 | D5: 0 | E5: 0 | F5: =C5*12 -> 0 | G5: =D5*12 -> 0 | H5: =E5*12 -> 0 | I5: Dentro da cota gratuita no piloto
A6: Integrações | B6: E-mail transacional com domínio próprio (SMTP) | C6: 0 | D6: 0 | E6: 90 | F6: =C6*12 -> 0 | G6: =D6*12 -> 0 | H6: =E6*12 -> 1080 | I6: Estimativa: planos gratuitos atendem o piloto
A7: Integrações | B7: Consulta de CNPJ (bases públicas) | C7: 0 | D7: 0 | E7: 0 | F7: =C7*12 -> 0 | G7: =D7*12 -> 0 | H7: =E7*12 -> 0 | I7: Gratuita
A8: Manutenção | B8: Desenvolvimento e correções | C8: =Premissas!B8*Premissas!B9 -> 240 | D8: =Premissas!C8*Premissas!C9 -> 720 | E8: =Premissas!D8*Premissas!D9 -> 1800 | F8: =C8*12 -> 2880 | G8: =D8*12 -> 8640 | H8: =E8*12 -> 21600 | I8: Horas × valor da hora (aba Premissas)
A9: Manutenção | B9: Moderação e suporte aos usuários | C9: =Premissas!B8*Premissas!B10 -> 240 | D9: =Premissas!C8*Premissas!C10 -> 900 | E9: =Premissas!D8*Premissas!D10 -> 2400 | F9: =C9*12 -> 2880 | G9: =D9*12 -> 10800 | H9: =E9*12 -> 28800 | I9: Horas × valor da hora (aba Premissas)
A10: Manutenção | B10: Backup e monitoramento | C10: 0 | D10: 20 | E10: 60 | F10: =C10*12 -> 0 | G10: =D10*12 -> 240 | H10: =E10*12 -> 720 | I10: Exportação periódica do Firestore e alertas; estimativa
A11: Marketing | B11: Anúncios em redes sociais | C11: =Premissas!B11 -> 0 | D11: =Premissas!C11 -> 150 | E11: =Premissas!D11 -> 500 | F11: =C11*12 -> 0 | G11: =D11*12 -> 1800 | H11: =E11*12 -> 6000 | I11: Aba Premissas
A12: Marketing | B12: Material gráfico (cartazes e panfletos) | C12: 25 | D12: 40 | E12: 100 | F12: =C12*12 -> 300 | G12: =D12*12 -> 480 | H12: =E12*12 -> 1200 | I12: Estimativa diluída por mês (impressão em lote)
A13: Marketing | B13: Ferramentas de design (versão gratuita) | C13: 0 | D13: 0 | E13: 0 | F13: =C13*12 -> 0 | G13: =D13*12 -> 0 | H13: =E13*12 -> 0 | I13: Canva gratuito
A14: TOTAL | C14: =SUM(C2:C13) -> 508.33333 | D14: =SUM(D2:D13) -> 1873.3333 | E14: =SUM(E2:E13) -> 5103.3333 | F14: =SUM(F2:F13) -> 6100 | G14: =SUM(G2:G13) -> 22480 | H14: =SUM(H2:H13) -> 61240
A16: Resumo por categoria (R$/ano)
A17: Categoria | F17: Piloto | G17: Crescimento | H17: Consolidado
A18: Domínio | F18: =SUMIF($A$2:$A$13,$A18,F$2:F$13) -> 40 | G18: =SUMIF($A$2:$A$13,$A18,G$2:G$13) -> 40 | H18: =SUMIF($A$2:$A$13,$A18,H$2:H$13) -> 40
A19: Hospedagem | F19: =SUMIF($A$2:$A$13,$A19,F$2:F$13) -> 0 | G19: =SUMIF($A$2:$A$13,$A19,G$2:G$13) -> 480 | H19: =SUMIF($A$2:$A$13,$A19,H$2:H$13) -> 1800
A20: Integrações | F20: =SUMIF($A$2:$A$13,$A20,F$2:F$13) -> 0 | G20: =SUMIF($A$2:$A$13,$A20,G$2:G$13) -> 0 | H20: =SUMIF($A$2:$A$13,$A20,H$2:H$13) -> 1080
A21: Manutenção | F21: =SUMIF($A$2:$A$13,$A21,F$2:F$13) -> 5760 | G21: =SUMIF($A$2:$A$13,$A21,G$2:G$13) -> 19680 | H21: =SUMIF($A$2:$A$13,$A21,H$2:H$13) -> 51120
A22: Marketing | F22: =SUMIF($A$2:$A$13,$A22,F$2:F$13) -> 300 | G22: =SUMIF($A$2:$A$13,$A22,G$2:G$13) -> 2280 | H22: =SUMIF($A$2:$A$13,$A22,H$2:H$13) -> 7200
A24: Custo de caixa/ano (sem horas de trabalho) | F24: =F14-C8*12-C9*12 -> 340 | G24: =G14-D8*12-D9*12 -> 3040 | H24: =H14-E8*12-E9*12 -> 10840 | I24: Se manutenção e moderação forem voluntárias (caso do TCC), este é o desembolso real.

Sheet Capacidade Firebase
A1: Indicador | B1: Piloto | C1: Crescimento | D1: Consolidado | E1: Observação
A2: Contas totais | B2: =Premissas!B2+Premissas!B3 -> 253 | C2: =Premissas!C2+Premissas!C3 -> 1010 | D2: =Premissas!D2+Premissas!D3 -> 5030
A3: Usuários ativos por dia | B3: =B2*Premissas!B4 -> 25.3 | C3: =C2*Premissas!C4 -> 80.8 | D3: =D2*Premissas!D4 -> 301.8
A4: Leituras por dia | B4: =B3*Premissas!B7*Premissas!B5 -> 11385 | C4: =C3*Premissas!C7*Premissas!C5 -> 36360 | D4: =D3*Premissas!D7*Premissas!D5 -> 135810 | E4: Usuários ativos × visitas × leituras por visita
A5: Escritas por dia | B5: =B3*Premissas!B7*Premissas!B6 -> 303.6 | C5: =C3*Premissas!C7*Premissas!C6 -> 969.6 | D5: =D3*Premissas!D7*Premissas!D6 -> 3621.6
A6: Uso da cota de leituras | B6: =B4/Premissas!B12 -> 0.2277 | C6: =C4/Premissas!C12 -> 0.7272 | D6: =D4/Premissas!D12 -> 2.7162
A7: Uso da cota de escritas | B7: =B5/Premissas!B13 -> 0.01518 | C7: =C5/Premissas!C13 -> 0.04848 | D7: =D5/Premissas!D13 -> 0.18108
A8: Situação | B8: =IF(MAX(B6,B7)<=0.8,"Dentro da cota gratuita",IF(MAX(B6,B7)<=1,"Atenção: perto do limite","Excede: usar plano Blaze")) -> Dentro da cota gratuita | C8: =IF(MAX(C6,C7)<=0.8,"Dentro da cota gratuita",IF(MAX(C6,C7)<=1,"Atenção: perto do limite","Excede: usar plano Blaze")) -> Dentro da cota gratuita | D8: =IF(MAX(D6,D7)<=0.8,"Dentro da cota gratuita",IF(MAX(D6,D7)<=1,"Atenção: perto do limite","Excede: usar plano Blaze")) -> Excede: usar plano Blaze | E8: Spark: ao exceder a cota, o serviço é suspenso até o fim do mês; Blaze cobra apenas o excedente.

Sheet Público estimado
A1: Indicador | B1: Valor | C1: Fonte / premissa
A2: População de Janaúba (MG) | B2: 70699 | C2: IBGE, Censo 2022
A3: Pessoas por domicílio (premissa) | B3: 3 | C3: Premissa de cálculo; ajustar com dado do IBGE se desejar
A4: Domicílios estimados em Janaúba | B4: =B2/B3 -> 23566.333 | C4: População ÷ pessoas por domicílio
A5: % de domicílios com algum grau de insegurança alimentar (Brasil, 2024) | B5: 0.242 | C5: IBGE, PNAD Contínua 2024 (média nacional; o município pode diferir)
A6: % com insegurança alimentar moderada ou grave (Brasil, 2024) | B6: 0.077 | C6: IBGE, PNAD Contínua 2024
A7: Domicílios com algum grau de insegurança alimentar (estimativa) | B7: =B4*B5 -> 5703.0527 | C7: Cálculo — estimativa, não dado municipal
A8: Domicílios com insegurança moderada ou grave (público prioritário) | B8: =B4*B6 -> 1814.6077 | C8: Cálculo — estimativa, não dado municipal
A9: Meta do piloto: % do público prioritário alcançado no 1º ano | B9: 0.1 | C9: Premissa
A10: Famílias que podem pedir ajuda no piloto (meta) | B10: =B8*B9 -> 181.46077 | C10: Prioritário × meta
A11: Contas de pessoas previstas (cenário Piloto) | B11: =Premissas!B2 -> 250 | C11: Aba Premissas (inclui doadores e beneficiários)
A12: ONGs previstas (cenário Piloto) | B12: =Premissas!B3 -> 3 | C12: Aba Premissas
A13: Custo de caixa por família atendida (R$/ano, Piloto) | B13: =IFERROR(Custos!F24/B10,0) -> 1.8736833 | C13: Custo de caixa do piloto ÷ famílias atendidas (meta)

Sheet Financiamento
A1: Fonte (opcional) | B1: Valor anual (R$) | C1: Observação
A2: Patrocínio de comércio local (cotas) | B2: 0 | C2: Edite: ex. nº de apoiadores × valor da cota
A3: Parceria com prefeitura / secretaria de assistência social | B3: 0 | C3: Apoio institucional ou cessão de divulgação
A4: Doações voluntárias para a manutenção da plataforma | B4: 0 | C4: Doação opcional, sem vínculo com a ajuda recebida
A5: Editais e fundos para tecnologia social | B5: 0 | C5: Pesquisar editais abertos
A6: Apoio do IFNMG (laboratório/projeto de extensão) | B6: 0 | C6: Hospedagem e horas de orientação como contrapartida
A8: Total de recursos previstos | B8: =SUM(B2:B6) -> 0
A9: Custo anual — Piloto (com horas) | B9: =Custos!F14 -> 6100
A10: Custo anual — Crescimento (com horas) | B10: =Custos!G14 -> 22480
A11: Saldo (recursos − custo Crescimento) | B11: =B8-B10 -> -22480
A13: Monetização: a plataforma NÃO deve cobrar de quem precisa de ajuda nem vender dados (LGPD). Manter 100% sem fins lucrativos.
